pyhdtoolkit/__init__.py
pyhdtoolkit/version.py
pyhdtoolkit/cpymadtools/__init__.py
pyhdtoolkit/cpymadtools/_generators.py
pyhdtoolkit/cpymadtools/constants.py
pyhdtoolkit/cpymadtools/coupling.py
pyhdtoolkit/cpymadtools/matching.py
pyhdtoolkit/cpymadtools/parameters.py
pyhdtoolkit/cpymadtools/ptc.py
pyhdtoolkit/cpymadtools/track.py
pyhdtoolkit/cpymadtools/tune.py
pyhdtoolkit/cpymadtools/twiss.py
pyhdtoolkit/cpymadtools/utils.py
pyhdtoolkit/cpymadtools/lhc/__init__.py
pyhdtoolkit/cpymadtools/lhc/_coupling.py
pyhdtoolkit/cpymadtools/lhc/_elements.py
pyhdtoolkit/cpymadtools/lhc/_errors.py
pyhdtoolkit/cpymadtools/lhc/_misc.py
pyhdtoolkit/cpymadtools/lhc/_powering.py
pyhdtoolkit/cpymadtools/lhc/_queries.py
pyhdtoolkit/cpymadtools/lhc/_routines.py
pyhdtoolkit/cpymadtools/lhc/_setup.py
pyhdtoolkit/cpymadtools/lhc/_twiss.py
pyhdtoolkit/maths/__init__.py
pyhdtoolkit/maths/stats_fitting.py
pyhdtoolkit/maths/utils.py
pyhdtoolkit/models/__init__.py
pyhdtoolkit/models/beam.py
pyhdtoolkit/models/htc.py
pyhdtoolkit/models/madx.py
pyhdtoolkit/optics/__init__.py
pyhdtoolkit/optics/beam.py
pyhdtoolkit/optics/rdt.py
pyhdtoolkit/optics/ripken.py
pyhdtoolkit/optics/twiss.py
pyhdtoolkit/plotting/__init__.py
pyhdtoolkit/plotting/aperture.py
pyhdtoolkit/plotting/crossing.py
pyhdtoolkit/plotting/envelope.py
pyhdtoolkit/plotting/lattice.py
pyhdtoolkit/plotting/layout.py
pyhdtoolkit/plotting/phasespace.py
pyhdtoolkit/plotting/tune.py
pyhdtoolkit/plotting/utils.py
pyhdtoolkit/plotting/sbs/__init__.py
pyhdtoolkit/plotting/sbs/coupling.py
pyhdtoolkit/plotting/sbs/phase.py
pyhdtoolkit/plotting/styles/__init__.py
pyhdtoolkit/plotting/styles/paper.py
pyhdtoolkit/plotting/styles/thesis.py
pyhdtoolkit/utils/__init__.py
pyhdtoolkit/utils/_misc.py
pyhdtoolkit/utils/cmdline.py
pyhdtoolkit/utils/contexts.py
pyhdtoolkit/utils/decorators.py
pyhdtoolkit/utils/htc_monitor.py
pyhdtoolkit/utils/logging.py
pyhdtoolkit-1.7.0.dist-info/METADATA
pyhdtoolkit-1.7.0.dist-info/WHEEL
pyhdtoolkit-1.7.0.dist-info/licenses/LICENSE
pyhdtoolkit-1.7.0.dist-info/RECORD
