Metadata-Version: 2.3
Name: pyhdtoolkit
Version: 1.7.0
Summary: An all-in-one toolkit package to ease my Python work in my PhD.
Project-URL: homepage, https://github.com/fsoubelet/PyhDToolkit
Project-URL: repository, https://github.com/fsoubelet/PyhDToolkit
Project-URL: documentation, https://fsoubelet.github.io/PyhDToolkit
Project-URL: changelog, https://fsoubelet.github.io/PyhDToolkit/release.html
Author-email: Felix Soubelet <felix.soubelet@cern.ch>
License: MIT
Keywords: Accelerator Physics,Docker,PHD,Physics Simulation,Visualisation
Classifier: Development Status :: 4 - Beta
Classifier: Intended Audience :: Science/Research
Classifier: License :: OSI Approved :: MIT License
Classifier: Natural Language :: English
Classifier: Programming Language :: Python
Classifier: Programming Language :: Python :: 3 :: Only
Classifier: Programming Language :: Python :: 3.8
Classifier: Programming Language :: Python :: 3.9
Classifier: Programming Language :: Python :: 3.10
Classifier: Programming Language :: Python :: 3.11
Classifier: Programming Language :: Python :: 3.12
Classifier: Programming Language :: Python :: Implementation :: CPython
Classifier: Topic :: Scientific/Engineering
Classifier: Topic :: Scientific/Engineering :: Physics
Classifier: Topic :: Scientific/Engineering :: Visualization
Classifier: Topic :: Utilities
Requires-Python: >=3.10
Requires-Dist: cpymad>=1.16
Requires-Dist: loguru<1.0
Requires-Dist: matplotlib>=3.7
Requires-Dist: numpy>=2.0
Requires-Dist: optics-functions>=0.1
Requires-Dist: pandas>=2.0
Requires-Dist: pendulum>=3.0
Requires-Dist: pydantic>=2.0
Requires-Dist: rich>=13.0
Requires-Dist: scipy>=1.6
Requires-Dist: tfs-pandas>=3.8
Provides-Extra: all
Requires-Dist: black>=24.0; extra == 'all'
Requires-Dist: coverage[toml]>=7.0; extra == 'all'
Requires-Dist: flaky>=3.5; extra == 'all'
Requires-Dist: isort>=5.10; extra == 'all'
Requires-Dist: joblib>=1.0; extra == 'all'
Requires-Dist: numba>=0.60.0; extra == 'all'
Requires-Dist: pytest-cov>=5.0; extra == 'all'
Requires-Dist: pytest-mpl>=0.14; extra == 'all'
Requires-Dist: pytest-randomly>=3.3; extra == 'all'
Requires-Dist: pytest-xdist>=3.0; extra == 'all'
Requires-Dist: pytest>=8.0; extra == 'all'
Requires-Dist: ruff>=0.5; extra == 'all'
Requires-Dist: sphinx-codeautolink>=0.14; extra == 'all'
Requires-Dist: sphinx-copybutton<1.0; extra == 'all'
Requires-Dist: sphinx-design>=0.6; extra == 'all'
Requires-Dist: sphinx-gallery<1.0; extra == 'all'
Requires-Dist: sphinx-issues>=4.0; extra == 'all'
Requires-Dist: sphinx-prompt>=1.5; extra == 'all'
Requires-Dist: sphinx-rtd-theme>=2.0; extra == 'all'
Requires-Dist: sphinx>=7.0; extra == 'all'
Requires-Dist: sphinxcontrib-bibtex>=2.4; extra == 'all'
Provides-Extra: dev
Requires-Dist: black>=24.0; extra == 'dev'
Requires-Dist: isort>=5.10; extra == 'dev'
Requires-Dist: ruff>=0.5; extra == 'dev'
Provides-Extra: docs
Requires-Dist: joblib>=1.0; extra == 'docs'
Requires-Dist: sphinx-codeautolink>=0.14; extra == 'docs'
Requires-Dist: sphinx-copybutton<1.0; extra == 'docs'
Requires-Dist: sphinx-design>=0.6; extra == 'docs'
Requires-Dist: sphinx-gallery<1.0; extra == 'docs'
Requires-Dist: sphinx-issues>=4.0; extra == 'docs'
Requires-Dist: sphinx-prompt>=1.5; extra == 'docs'
Requires-Dist: sphinx-rtd-theme>=2.0; extra == 'docs'
Requires-Dist: sphinx>=7.0; extra == 'docs'
Requires-Dist: sphinxcontrib-bibtex>=2.4; extra == 'docs'
Provides-Extra: test
Requires-Dist: coverage[toml]>=7.0; extra == 'test'
Requires-Dist: flaky>=3.5; extra == 'test'
Requires-Dist: numba>=0.60.0; extra == 'test'
Requires-Dist: pytest-cov>=5.0; extra == 'test'
Requires-Dist: pytest-mpl>=0.14; extra == 'test'
Requires-Dist: pytest-randomly>=3.3; extra == 'test'
Requires-Dist: pytest-xdist>=3.0; extra == 'test'
Requires-Dist: pytest>=8.0; extra == 'test'
